cloudbees/__init__.py
cloudbees/_version.py
cloudbees/provider.py
cloudbees_openfeature_provider_python-0.1.7.dist-info/LICENSE.txt
cloudbees_openfeature_provider_python-0.1.7.dist-info/METADATA
cloudbees_openfeature_provider_python-0.1.7.dist-info/WHEEL
cloudbees_openfeature_provider_python-0.1.7.dist-info/top_level.txt
cloudbees_openfeature_provider_python-0.1.7.dist-info/RECORD
